TOPSIS_KARTIK_101803702/__init__.py
TOPSIS_KARTIK_101803702/topsis.py
TOPSIS_KARTIK_101803702-0.0.1.dist-info/LICENSE.txt
TOPSIS_KARTIK_101803702-0.0.1.dist-info/METADATA
TOPSIS_KARTIK_101803702-0.0.1.dist-info/WHEEL
TOPSIS_KARTIK_101803702-0.0.1.dist-info/top_level.txt
TOPSIS_KARTIK_101803702-0.0.1.dist-info/RECORD
