Metadata-Version: 2.1
Name: TOPSIS-KARTIK-101803702
Version: 0.0.1
Summary: This package takes a .csv file as input and calculate topsis score of all entries and rank them according to the topsis score
Home-page: UNKNOWN
Author: kartik
Author-email: singlakartik513@gmail.com
License: MIT
Keywords: topsis,rank,data science
Platform: UNKNOWN
Classifier: Programming Language :: Python :: 3
Classifier: License :: OSI Approved :: MIT License
Classifier: Operating System :: OS Independent
